{"children":[{"children":[{"detail":0,"format":0,"mode":"normal","style":"","text":"Nouns EsportsとBLVKHVNDでは、EVO Japanに参加する10名のプレイヤーを募集しております！選ばれた選手には、300ドル、Nouns Esports x BLVKHVNDジャージ、グッズパックが贈られます。﻿","type":"text","version":1}],"direction":"ltr","format":"","indent":0,"type":"paragraph","version":1,"textFormat":0},{"children":[{"detail":0,"format":0,"mode":"normal","style":"","text":"Requirements:","type":"text","version":1}],"direction":"ltr","format":"","indent":0,"type":"paragraph","version":1,"textFormat":0},{"children":[{"detail":0,"format":0,"mode":"normal","style":"","text":"Nouns Esportsのイベント関連の投稿をソーシャルメディアでシェアすること","type":"text","version":1}],"direction":"ltr","format":"","indent":0,"type":"paragraph","version":1,"textFormat":0},{"children":[{"detail":0,"format":0,"mode":"normal","style":"","text":"EVO JapanでNounsとBLVKHVNDの代表にふさわしい理由や、あなたのゲームでの実績について、企画書を提出すること","type":"text","version":1}],"direction":"ltr","format":"","indent":0,"type":"paragraph","version":1,"textFormat":0},{"children":[{"detail":0,"format":0,"mode":"normal","style":"","text":"Extra Opportunity:","type":"text","version":1}],"direction":"ltr","format":"","indent":0,"type":"paragraph","version":1,"textFormat":0},{"children":[{"detail":0,"format":0,"mode":"normal","style":"","text":"スト6か鉄拳8の成績優秀者には、EVOラスベガスへの参加費として2000ドルがゲットできる!","type":"text","version":1}],"direction":"ltr","format":"","indent":0,"type":"paragraph","version":1,"textFormat":0},{"children":[{"detail":0,"format":0,"mode":"normal","style":"","text":"FGCベテランへ:","type":"text","version":1}],"direction":"ltr","format":"","indent":0,"type":"paragraph","version":1,"textFormat":0},{"children":[{"children":[{"detail":0,"format":0,"mode":"normal","style":"","text":"https://nouns.gg/signup-jp","type":"text","version":1}],"direction":"ltr","format":"","indent":0,"type":"link","version":1,"rel":"noreferrer","target":"_blank","title":null,"url":"https://nouns.gg/signup-jp"},{"detail":0,"format":0,"mode":"normal","style":"","text":" に投票者として登録し、勝者を選ぶのにご協力ください。","type":"text","version":1}],"direction":"ltr","format":"","indent":0,"type":"paragraph","version":1,"textFormat":0},{"children":[{"detail":0,"format":0,"mode":"normal","style":"","text":"Nouns Esports x BLVKHVNDの代表として、ゲーミングキャリアを次のレベルに引き上げるために、今すぐ応募ください！","type":"text","version":1}],"direction":"ltr","format":"","indent":0,"type":"paragraph","version":1,"textFormat":0},{"children":[{"children":[{"detail":0,"format":0,"mode":"normal","style":"","text":"Nouns Esports","type":"text","version":1}],"direction":"ltr","format":"","indent":0,"type":"link","version":1,"rel":"noreferrer","target":"_blank","title":null,"url":"https://twitter.com/nounsesports"},{"detail":0,"format":0,"mode":"normal","style":"","text":" & ","type":"text","version":1},{"children":[{"detail":0,"format":0,"mode":"normal","style":"","text":"BLVKHVND","type":"text","version":1}],"direction":"ltr","format":"","indent":0,"type":"link","version":1,"rel":"noreferrer","target":"_blank","title":null,"url":"https://twitter.com/BLVKHVND"},{"detail":0,"format":0,"mode":"normal","style":"","text":" をフォローしてください。","type":"text","version":1}],"direction":"ltr","format":"","indent":0,"type":"paragraph","version":1,"textFormat":0}],"direction":"ltr","format":"","indent":0,"type":"root","version":1}